{
	"!excluded": "no",
	"matchId": "3991283",
	"player": {
		"895929": {
			"12098256": {
				"blocks": 2,
				"name": "Windfury",
				"prespp": 11,
				"turns": 12,
				"type": "R"
			},
			"12098257": {
				"blocks": 13,
				"name": "Clawchest",
				"prespp": 31,
				"turns": 17,
				"type": "R"
			},
			"12098258": {
				"blocks": 3,
				"name": "Silverscar",
				"prespp": 14,
				"turns": 17,
				"type": "R"
			},
			"12098263": {
				"blocks": 7,
				"name": "Silverstriker",
				"prespp": 17,
				"turns": 17,
				"type": "R"
			},
			"12098289": {
				"blocks": 4,
				"name": "Crowripper",
				"prespp": 10,
				"rush": 8,
				"spp": 3,
				"td": 1,
				"turns": 17,
				"type": "R"
			},
			"12098294": {
				"blocks": 3,
				"name": "Blackchewer",
				"prespp": 9,
				"rush": 2,
				"spp": 3,
				"td": 1,
				"turns": 16,
				"type": "R"
			},
			"12098297": {
				"blocks": 1,
				"name": "Duskdigger",
				"prespp": 20,
				"rush": 22,
				"turns": 13,
				"type": "R"
			},
			"12136367": {
				"blocks": 8,
				"name": "Fangsnapper Jr",
				"turns": 16,
				"type": "R"
			},
			"12166472": {
				"blocks": 6,
				"name": "Fangsnapper Jr Jr",
				"turns": 16,
				"type": "R"
			},
			"12184769": {
				"blocks": 2,
				"comp": 1,
				"mvp": 1,
				"name": "Barbedbreath",
				"pass": 3,
				"prespp": 8,
				"rush": 4,
				"spp": 6,
				"turns": 17,
				"type": "R"
			},
			"12265899": {
				"blocks": 1,
				"name": "Dustbinder",
				"turns": 17,
				"type": "R"
			},
			"12295244": {
				"name": "Broadreaper",
				"turns": 1,
				"type": "R"
			},
			"12295253": {
				"name": "Heartbuster",
				"type": "R"
			}
		},
		"898574": {
			"12140311": {
				"blocks": 9,
				"name": "Hemlock Wyatt",
				"prespp": 6,
				"turns": 16,
				"type": "R"
			},
			"12140313": {
				"blocks": 8,
				"cas": 1,
				"mvp": 1,
				"name": "Arsenic William",
				"prespp": 16,
				"rush": 9,
				"spp": 10,
				"td": 1,
				"turns": 15,
				"type": "R"
			},
			"12140318": {
				"blocks": 5,
				"name": "Dimefox Winston",
				"prespp": 20,
				"turns": 16,
				"type": "R"
			},
			"12140321": {
				"blocks": 4,
				"comp": 3,
				"name": "Hydrazine Wendall",
				"pass": 1,
				"prespp": 13,
				"rush": 10,
				"spp": 3,
				"turns": 12,
				"type": "R"
			},
			"12140327": {
				"name": "Lactonitrile Bernice",
				"prespp": 8,
				"turns": 16,
				"type": "R"
			},
			"12140330": {
				"name": "Lindane Salvatore",
				"prespp": 2,
				"turns": 6,
				"type": "R"
			},
			"12140331": {
				"blocks": 3,
				"name": "Malononitrile Sebastian",
				"turns": 16,
				"type": "R"
			},
			"12140364": {
				"name": "Methomyl Samuel",
				"prespp": 6,
				"turns": 3,
				"type": "R"
			},
			"12140428": {
				"blocks": 4,
				"name": "Phenol Sinclair",
				"prespp": 2,
				"turns": 12,
				"type": "R"
			},
			"12140430": {
				"blocks": 2,
				"name": "Piperidine Scarlett",
				"prespp": 7,
				"turns": 10,
				"type": "R"
			},
			"12146724": {
				"name": "Anchorman",
				"prespp": 2,
				"turns": 2,
				"type": "R"
			},
			"12180127": {
				"name": "Botulinum Bo",
				"prespp": 10,
				"turns": 16,
				"type": "R"
			},
			"12234728": {
				"name": "Nightshade Simi",
				"turns": 4,
				"type": "R"
			},
			"12281353": {
				"name": "Ph'rn \"Gent\" Kbrrcllr",
				"turns": 3,
				"type": "R"
			}
		}
	},
	"replayId": "1071314",
	"team": {
		"895929": {
			"blocks": 50,
			"cas": 0,
			"casdiff": -1,
			"comp": 1,
			"fouls": 0,
			"int": 0,
			"mvp": 1,
			"name": "Fangsnapper's Clawpack",
			"pass": 3,
			"prespp": 120,
			"prestige": 0,
			"pts": 3,
			"r": "W",
			"rush": 36,
			"score": 2,
			"scorediff": 1,
			"td": 2,
			"tddiff": 1,
			"turns": 176
		},
		"898574": {
			"blocks": 35,
			"cas": 1,
			"casdiff": 1,
			"comp": 3,
			"fouls": 0,
			"int": 0,
			"mvp": 1,
			"name": "Revenge Street Reapers",
			"pass": 1,
			"prespp": 92,
			"prestige": 0,
			"pts": 0,
			"r": "L",
			"rush": 19,
			"score": 1,
			"scorediff": -1,
			"td": 1,
			"tddiff": -1,
			"turns": 147
		}
	}
}