{
	"!excluded": "no",
	"!locked": "yes",
	"matchId": "4025255",
	"player_performance": {
		"909759": {
			"12314474": {
				"blk": 7,
				"cas": 1,
				"mvp": 1,
				"name": "Helewise",
				"prespp": 11,
				"spp": 7,
				"tur": 16,
				"type": "R"
			},
			"12314475": {
				"blk": 3,
				"name": "Aimee",
				"prespp": 23,
				"rus": 23,
				"tur": 15,
				"type": "R"
			},
			"12314476": {
				"blk": 1,
				"cps": 1,
				"name": "Naeva",
				"pas": 1,
				"prespp": 27,
				"rus": 3,
				"spp": 1,
				"tur": 16,
				"type": "R"
			},
			"12314477": {
				"blk": 4,
				"cps": 1,
				"name": "Roesia",
				"pas": 1,
				"prespp": 19,
				"rus": 3,
				"spp": 1,
				"tur": 16,
				"type": "R"
			},
			"12314479": {
				"blk": 2,
				"name": "Odlette",
				"prespp": 1,
				"tur": 10,
				"type": "R"
			},
			"12314480": {
				"blk": 2,
				"fou": 1,
				"name": "Sabine",
				"prespp": 8,
				"tur": 16,
				"type": "R"
			},
			"12314481": {
				"name": "Monique",
				"prespp": 3,
				"type": "R"
			},
			"12314482": {
				"blk": 1,
				"name": "Antionette",
				"prespp": 2,
				"tur": 14,
				"type": "R"
			},
			"12314483": {
				"name": "Chantal",
				"prespp": 2,
				"tur": 7,
				"type": "R"
			},
			"12353445": {
				"blk": 4,
				"name": "Edmee",
				"prespp": 6,
				"tur": 10,
				"type": "R"
			},
			"12488126": {
				"blk": 1,
				"name": "Sean Silentfist",
				"retired": true,
				"tur": 9,
				"type": "J"
			}
		},
		"915893": {
			"12410997": {
				"blk": 2,
				"name": "White Fangs",
				"tur": 10,
				"type": "R"
			},
			"12410998": {
				"blk": 3,
				"name": "Thick Hide",
				"prespp": 7,
				"tur": 16,
				"type": "R"
			},
			"12410999": {
				"blk": 3,
				"mvp": 1,
				"name": "Sharpclaws",
				"prespp": 2,
				"spp": 5,
				"tur": 16,
				"type": "R"
			},
			"12411000": {
				"blk": 6,
				"name": "Swiftslash",
				"prespp": 7,
				"rus": 39,
				"spp": 6,
				"tds": 2,
				"tur": 16,
				"type": "R"
			},
			"12411001": {
				"blk": 3,
				"name": "Chargtooth",
				"prespp": 10,
				"tur": 16,
				"type": "R"
			},
			"12411002": {
				"blk": 4,
				"name": "Summercharge",
				"prespp": 2,
				"rus": 2,
				"tur": 16,
				"type": "R"
			},
			"12411003": {
				"blk": 6,
				"name": "Danel",
				"prespp": 6,
				"tur": 16,
				"type": "R"
			},
			"12411004": {
				"blk": 4,
				"name": "Isnagard",
				"tur": 16,
				"type": "R"
			},
			"12411005": {
				"blk": 1,
				"name": "Landerous",
				"prespp": 2,
				"tur": 16,
				"type": "R"
			},
			"12411006": {
				"blk": 1,
				"name": "Vladimoff",
				"tur": 8,
				"type": "R"
			},
			"12411007": {
				"name": "Madrigard",
				"prespp": 2,
				"type": "R"
			},
			"915893M1": {
				"blk": 8,
				"name": "Merc Kurnocervus 1",
				"tur": 16,
				"type": "M"
			}
		}
	},
	"replayId": "1110445",
	"team_performance": {
		"909759": {
			"cas": 1,
			"casdiff": 1,
			"name": "Malefic Mimes",
			"rsym": "L",
			"score": 0,
			"scorediff": -2,
			"tds": 0,
			"tdsdiff": -2
		},
		"915893": {
			"cas": 0,
			"casdiff": -1,
			"name": "Loren's Rebuke",
			"rsym": "W",
			"score": 2,
			"scorediff": 2,
			"tds": 2,
			"tdsdiff": 2
		}
	}
}