{
	"!excluded": "no",
	"!locked": "yes",
	"matchId": "3922058",
	"modified": "2017-08-01 12:48:26",
	"player_performance": {},
	"replayId": "990605",
	"team_performance": {
		"4": {
			"cas": 1,
			"casdiff": -3,
			"id": "874452",
			"name": "Way of the Dragon",
			"prestige": 0,
			"pts": 0,
			"rsym": "L",
			"score": 1,
			"scorediff": -1,
			"tds": 1,
			"tdsdiff": -1
		},
		"5": {
			"cas": 4,
			"casdiff": 3,
			"id": "873349",
			"name": "Reik River Kicking Mules",
			"prestige": 0,
			"pts": 2,
			"rsym": "W",
			"score": 2,
			"scorediff": 1,
			"tds": 2,
			"tdsdiff": 1
		}
	}
}