{
	"!excluded": "no",
	"matchId": "3849800",
	"player": {
		"855072": {
			"11445733": {
				"blocks": 6,
				"name": "Jack",
				"prespp": 9,
				"turns": 11,
				"type": "R"
			},
			"11445734": {
				"blocks": 9,
				"name": "Annie",
				"prespp": 3,
				"turns": 18,
				"type": "R"
			},
			"11445735": {
				"blocks": 13,
				"cas": 1,
				"name": "Katheen",
				"prespp": 9,
				"spp": 2,
				"turns": 18,
				"type": "R"
			},
			"11445736": {
				"blocks": 2,
				"name": "Teddy",
				"prespp": 17,
				"turns": 6,
				"type": "R"
			},
			"11445737": {
				"name": "Morgan le Fay",
				"prespp": 2,
				"turns": 18,
				"type": "R"
			},
			"11445738": {
				"blocks": 3,
				"name": "Merlin",
				"rush": 20,
				"spp": 3,
				"td": 1,
				"turns": 14,
				"type": "R"
			},
			"11445741": {
				"blocks": 3,
				"name": "Queen Guinevere",
				"rush": 2,
				"turns": 13,
				"type": "R"
			},
			"11445745": {
				"name": "Thiebaut l'Amy",
				"prespp": 2,
				"type": "R"
			},
			"11445746": {
				"name": "Marguarite de la Riviere",
				"prespp": 5,
				"type": "R"
			},
			"11445747": {
				"blocks": 1,
				"mvp": 1,
				"name": "Blanchet Poupart",
				"spp": 5,
				"turns": 18,
				"type": "R"
			},
			"11494644": {
				"name": "King Arthur Junior",
				"turns": 1,
				"type": "R"
			},
			"11494645": {
				"blocks": 6,
				"name": "Cory Strongbrook",
				"turns": 15,
				"type": "J"
			}
		},
		"855120": {
			"11446496": {
				"blocks": 1,
				"name": "Aethedi",
				"prespp": 3,
				"rush": 30,
				"spp": 6,
				"td": 2,
				"turns": 17,
				"type": "R"
			},
			"11446497": {
				"blocks": 11,
				"cas": 3,
				"name": "Zunrec Greatbone",
				"spp": 6,
				"turns": 16,
				"type": "R"
			},
			"11446499": {
				"blocks": 11,
				"cas": 1,
				"name": "Oedia",
				"prespp": 1,
				"rush": 13,
				"spp": 5,
				"td": 1,
				"turns": 17,
				"type": "R"
			},
			"11446516": {
				"blocks": 4,
				"cas": 1,
				"name": "Manslicer the Vile",
				"prespp": 4,
				"spp": 2,
				"turns": 17,
				"type": "R"
			},
			"11446518": {
				"blocks": 3,
				"name": "Odorico De Leo",
				"prespp": 2,
				"turns": 14,
				"type": "R"
			},
			"11446519": {
				"blocks": 5,
				"name": "Verano Ragazzo",
				"prespp": 10,
				"turns": 17,
				"type": "R"
			},
			"11446521": {
				"blocks": 3,
				"name": "Ladislao Celano",
				"prespp": 12,
				"turns": 16,
				"type": "R"
			},
			"11446522": {
				"name": "Nicola Valeri",
				"turns": 3,
				"type": "R"
			},
			"11493958": {
				"blocks": 2,
				"mvp": 1,
				"name": "Pietro Lisio",
				"spp": 5,
				"turns": 17,
				"type": "R"
			},
			"11493959": {
				"blocks": 1,
				"name": "Evelina Burgio",
				"turns": 17,
				"type": "R"
			},
			"11494637": {
				"blocks": 9,
				"comp": 1,
				"name": "Ghezioc",
				"pass": 1,
				"rush": 1,
				"spp": 1,
				"turns": 17,
				"type": "R"
			}
		}
	},
	"replayId": "907266",
	"team": {
		"855072": {
			"blocks": 43,
			"cas": 1,
			"casdiff": -4,
			"comp": 0,
			"fouls": 0,
			"int": 0,
			"mvp": 1,
			"name": "Carcassonne Knights",
			"pass": 0,
			"prespp": 47,
			"prestige": 0,
			"pts": 0,
			"r": "L",
			"rush": 22,
			"score": 1,
			"scorediff": -2,
			"td": 1,
			"tddiff": -2,
			"turns": 132
		},
		"855120": {
			"blocks": 50,
			"cas": 5,
			"casdiff": 4,
			"comp": 1,
			"fouls": 0,
			"int": 0,
			"mvp": 1,
			"name": "Trantio Dragon Hawks",
			"pass": 1,
			"prespp": 32,
			"prestige": 3,
			"pts": 3,
			"r": "W",
			"rush": 44,
			"score": 3,
			"scorediff": 2,
			"td": 3,
			"tddiff": 2,
			"turns": 168
		}
	}
}