{
	"cost": 140000,
	"doubleSkills": [
		"A",
		"P",
		"G"
	],
	"gender": "neutral",
	"icon": 604514,
	"iconLetter": "BB",
	"id": "8157",
	"name": "Blood Beast of Khorne III",
	"normalSkills": [
		"M",
		"S"
	],
	"portrait": 555093,
	"quantity": 1,
	"race": null,
	"roster": 1029,
	"secretweapon": "0",
	"skillSet": "2016",
	"skills": [
		"Ball & Chain",
		"Claw",
		"No Hands",
		"Regeneration",
		"Thick Skull",
		"Mighty Blow"
	],
	"stats": {
		"AG": 2,
		"AV": 9,
		"MA": 6,
		"PA": null,
		"ST": 6
	},
	"thrall": "false",
	"title": "Blood Beast of Khorne III",
	"type": "normal",
	"undead": "false"
}