{
	"!excluded": "no",
	"matchId": "3933376",
	"player": {
		"874966": {
			"11764899": {
				"name": "Benethor",
				"prespp": 21,
				"turns": 3,
				"type": "R"
			},
			"11764901": {
				"name": "Danesthos",
				"prespp": 6,
				"turns": 4,
				"type": "R"
			},
			"11764915": {
				"name": "Finavar",
				"prespp": 6,
				"turns": 6,
				"type": "R"
			},
			"11764917": {
				"blocks": 2,
				"comp": 1,
				"name": "Thuralin",
				"pass": -2,
				"prespp": 10,
				"rush": 2,
				"spp": 1,
				"turns": 16,
				"type": "R"
			},
			"11764919": {
				"name": "Lemsas",
				"prespp": 1,
				"type": "R"
			},
			"11764921": {
				"blocks": 6,
				"name": "Morlanna",
				"prespp": 39,
				"rush": 3,
				"turns": 16,
				"type": "R"
			},
			"11836559": {
				"blocks": 2,
				"name": "Vanhir",
				"prespp": 39,
				"turns": 4,
				"type": "R"
			},
			"11900737": {
				"blocks": 6,
				"cas": 1,
				"mvp": 1,
				"name": "Beliath the Grimm",
				"prespp": 2,
				"spp": 7,
				"turns": 16,
				"type": "B"
			},
			"11938500": {
				"name": "Mereia",
				"prespp": 9,
				"turns": 9,
				"type": "R"
			},
			"11967724": {
				"name": "Hauclir",
				"turns": 1,
				"type": "R"
			},
			"11967727": {
				"name": "Yorick Whiteorc",
				"turns": 10,
				"type": "J"
			}
		},
		"876774": {
			"11791176": {
				"blocks": 8,
				"cas": 1,
				"name": "Mather Teresa of Diesdolf",
				"prespp": 17,
				"spp": 2,
				"turns": 16,
				"type": "R"
			},
			"11791177": {
				"blocks": 2,
				"cas": 1,
				"fouls": 1,
				"name": "Saint Agnes \"The Comet\"",
				"prespp": 8,
				"rush": 8,
				"spp": 2,
				"turns": 16,
				"type": "R"
			},
			"11791215": {
				"blocks": 3,
				"name": "Ludmilla \"The Redeemed\"",
				"prespp": 16,
				"turns": 16,
				"type": "R"
			},
			"11791216": {
				"blocks": 5,
				"fouls": 1,
				"name": "Carol \"Divine Punishment\"",
				"prespp": 9,
				"turns": 16,
				"type": "R"
			},
			"11791220": {
				"blocks": 6,
				"cas": 1,
				"mvp": 1,
				"name": "Berta \"The Humble Daughter\"",
				"prespp": 17,
				"spp": 7,
				"turns": 16,
				"type": "R"
			},
			"11791224": {
				"blocks": 2,
				"name": "Ingrid \"Blind Faith\"",
				"prespp": 7,
				"rush": 15,
				"spp": 6,
				"td": 2,
				"turns": 16,
				"type": "R"
			},
			"11791226": {
				"fouls": 2,
				"name": "Luisa \"The Martyr\"",
				"turns": 11,
				"type": "R"
			},
			"11791229": {
				"name": "Johanna \"Silent Devotion\"",
				"type": "R"
			},
			"11791244": {
				"fouls": 1,
				"name": "Grisolda \"Last Pilgrimage\"",
				"prespp": 2,
				"turns": 16,
				"type": "R"
			},
			"11890580": {
				"dead": [
					1,
					8,
					"blocked",
					"11900737"
				],
				"fouls": 1,
				"name": "Gretha \"Innocent Heart\"",
				"prespp": 2,
				"retired": true,
				"rush": 2,
				"turns": 8,
				"type": "R"
			},
			"11898482": {
				"blocks": 1,
				"fouls": 1,
				"name": "Caterina \"Righteous Judgement\"",
				"prespp": 3,
				"turns": 12,
				"type": "R"
			},
			"11928024": {
				"name": "Rosetta \"Rose Thorn\"",
				"prespp": 6,
				"type": "R"
			},
			"11928026": {
				"fouls": 2,
				"name": "Olga \"Iron Cilice\"",
				"rush": 9,
				"turns": 16,
				"type": "R"
			}
		}
	},
	"replayId": "1003804",
	"team": {
		"874966": {
			"blocks": 16,
			"cas": 1,
			"casdiff": -2,
			"comp": 1,
			"fouls": 0,
			"int": 0,
			"mvp": 1,
			"name": "Modryn's Midnight Meddlers",
			"pass": -2,
			"prespp": 133,
			"prestige": 0,
			"pts": 0,
			"r": "L",
			"rush": 5,
			"score": 0,
			"scorediff": -2,
			"td": 0,
			"tddiff": -2,
			"turns": 85
		},
		"876774": {
			"blocks": 27,
			"cas": 3,
			"casdiff": 2,
			"comp": 0,
			"fouls": 9,
			"int": 0,
			"mvp": 1,
			"name": "Congregation of Holy Touchdown",
			"pass": 0,
			"prespp": 87,
			"prestige": 0,
			"pts": 3,
			"r": "W",
			"rush": 34,
			"score": 2,
			"scorediff": 2,
			"td": 2,
			"tddiff": 2,
			"turns": 159
		}
	}
}