{
	"!excluded": "no",
	"!locked": "yes",
	"matchId": "4063090",
	"player_performance": {
		"854600": {
			"11439806": {
				"blk": 1,
				"name": "Hernando Celador",
				"prespp": 14,
				"tur": 16,
				"type": "R"
			},
			"11439812": {
				"dead": [
					1,
					3,
					"blocked",
					"12537777"
				],
				"name": "Enrico Zapador",
				"prespp": 24,
				"tur": 3,
				"type": "R"
			},
			"11439814": {
				"blk": 5,
				"name": "Manuel Grandegolpe",
				"prespp": 78,
				"tur": 8,
				"type": "R"
			},
			"11698849": {
				"blk": 2,
				"name": "Javier Ladron",
				"prespp": 87,
				"rus": 9,
				"spp": 3,
				"tds": 1,
				"tur": 11,
				"type": "R"
			},
			"11780487": {
				"fou": 1,
				"name": "Reinaldo Halcon",
				"prespp": 7,
				"tur": 11,
				"type": "R"
			},
			"11876840": {
				"blk": 1,
				"cps": 1,
				"name": "Velasco Estibador",
				"pas": 7,
				"prespp": 64,
				"spp": 1,
				"tur": 10,
				"type": "R"
			},
			"11884680": {
				"name": "Basilio Mortalmente",
				"prespp": 92,
				"type": "R"
			},
			"11944052": {
				"name": "Francisco Portero",
				"prespp": 44,
				"tur": 13,
				"type": "R"
			},
			"12154538": {
				"blk": 9,
				"cas": 1,
				"name": "Vicente Hierromano",
				"prespp": 92,
				"spp": 2,
				"tur": 12,
				"type": "R"
			},
			"12362443": {
				"blk": 6,
				"name": "Armando Fuerte",
				"prespp": 27,
				"tur": 6,
				"type": "R"
			},
			"12437610": {
				"blk": 1,
				"name": "Thiago Ermitano",
				"tur": 11,
				"type": "R"
			},
			"12503392": {
				"name": "Jacobo Adusto",
				"prespp": 13,
				"tur": 1,
				"type": "R"
			},
			"12528251": {
				"blk": 7,
				"name": "Jorge Chaquetear",
				"prespp": 7,
				"rus": 8,
				"spp": 3,
				"tds": 1,
				"tur": 16,
				"type": "R"
			},
			"12528711": {
				"name": "Esteban Bromista",
				"tur": 2,
				"type": "R"
			},
			"12624234": {
				"blk": 1,
				"name": "Pablo Ciego",
				"prespp": 5,
				"tur": 7,
				"type": "R"
			},
			"12635208": {
				"blk": 3,
				"cas": 1,
				"mvp": 1,
				"name": "Jorge Agotado",
				"spp": 7,
				"tur": 16,
				"type": "R"
			}
		},
		"874317": {
			"11754410": {
				"blk": 8,
				"cas": 2,
				"name": "Odracon The Procreator",
				"prespp": 88,
				"spp": 4,
				"tur": 13,
				"type": "R"
			},
			"11754414": {
				"fou": 2,
				"name": "Lug",
				"prespp": 7,
				"tur": 1,
				"type": "R"
			},
			"11754417": {
				"blk": 7,
				"name": "Cethlenn",
				"prespp": 7,
				"tur": 16,
				"type": "R"
			},
			"11754418": {
				"blk": 1,
				"name": "Tethra",
				"prespp": 32,
				"tur": 5,
				"type": "R"
			},
			"11904321": {
				"blk": 4,
				"name": "Dilek",
				"prespp": 74,
				"rus": 41,
				"spp": 6,
				"tds": 2,
				"tur": 16,
				"type": "R"
			},
			"12047952": {
				"blk": 8,
				"name": "Slough Feg",
				"prespp": 77,
				"tur": 12,
				"type": "R"
			},
			"12126092": {
				"name": "Hadiz",
				"prespp": 57,
				"type": "R"
			},
			"12239695": {
				"blk": 12,
				"name": "Moloch the 3rd",
				"prespp": 60,
				"tur": 16,
				"type": "R"
			},
			"12340697": {
				"name": "Foulloch",
				"tur": 8,
				"type": "R"
			},
			"12537775": {
				"blk": 6,
				"name": "Balor The Everdying",
				"prespp": 15,
				"tur": 9,
				"type": "R"
			},
			"12537776": {
				"blk": 3,
				"mvp": 1,
				"name": "Cromcraug",
				"prespp": 2,
				"spp": 5,
				"tur": 12,
				"type": "R"
			},
			"12537777": {
				"blk": 5,
				"cas": 1,
				"name": "Kakt",
				"prespp": 7,
				"spp": 2,
				"tur": 16,
				"type": "R"
			},
			"12618155": {
				"blk": 4,
				"name": "Finn Fimm",
				"tur": 16,
				"type": "R"
			},
			"12624220": {
				"blk": 1,
				"fou": 1,
				"name": "Medb",
				"tur": 2,
				"type": "R"
			}
		}
	},
	"replayId": "1153768",
	"team_performance": {
		"854600": {
			"cas": 2,
			"casdiff": -3,
			"name": "Montetriste Noblemen",
			"prestige": 1,
			"pts": 1,
			"rsym": "D",
			"score": 2,
			"scorediff": 0,
			"tds": 2,
			"tdsdiff": 0
		},
		"874317": {
			"cas": 5,
			"casdiff": 3,
			"name": "Misty Isle Gators",
			"prestige": 1,
			"pts": 1,
			"rsym": "D",
			"score": 2,
			"scorediff": 0,
			"tds": 2,
			"tdsdiff": 0
		}
	}
}