{
	"!excluded": "no",
	"!locked": "yes",
	"matchId": "4043172",
	"player_performance": {
		"919573": {
			"12469183": {
				"blk": 1,
				"name": "Tornbull",
				"prespp": 13,
				"tur": 3,
				"type": "B"
			},
			"12469184": {
				"blk": 7,
				"name": "Blightbasher",
				"prespp": 11,
				"tur": 16,
				"type": "B"
			},
			"12469185": {
				"blk": 8,
				"cas": 1,
				"name": "Warpserker",
				"prespp": 21,
				"spp": 2,
				"tur": 14,
				"type": "B"
			},
			"12469186": {
				"blk": 10,
				"name": "Toerot",
				"prespp": 25,
				"tur": 12,
				"type": "B"
			},
			"12469191": {
				"name": "Tech Toetacker",
				"pas": 1,
				"prespp": 17,
				"rus": 18,
				"spp": 3,
				"tds": 1,
				"tur": 16,
				"type": "R"
			},
			"12469192": {
				"fou": 1,
				"name": "Znukch Clothclaw",
				"prespp": 6,
				"tur": 16,
				"type": "R"
			},
			"12469194": {
				"blk": 1,
				"name": "Crenq Brightear",
				"prespp": 7,
				"rus": 13,
				"spp": 3,
				"tds": 1,
				"tur": 13,
				"type": "R"
			},
			"12469210": {
				"name": "Srotch Firebaster",
				"prespp": 3,
				"tur": 5,
				"type": "R"
			},
			"12539782": {
				"blk": 2,
				"mvp": 1,
				"name": "Krulk Needlehand",
				"prespp": 8,
				"rus": 6,
				"spp": 8,
				"tds": 1,
				"tur": 16,
				"type": "R"
			},
			"12577931": {
				"blk": 1,
				"name": "Tristan Hideousfur",
				"prespp": 2,
				"tur": 7,
				"type": "R"
			},
			"12578261": {
				"blk": 3,
				"name": "Martin Goldspike",
				"retired": true,
				"tur": 16,
				"type": "J"
			}
		},
		"923590": {
			"12531622": {
				"blk": 8,
				"cas": 2,
				"name": "Lelak The Corruptor",
				"spp": 4,
				"tur": 16,
				"type": "R"
			},
			"12531623": {
				"blk": 12,
				"name": "Pezis Bonecall",
				"tur": 15,
				"type": "R"
			},
			"12531624": {
				"blk": 11,
				"name": "Pravras Deathhand",
				"tur": 16,
				"type": "R"
			},
			"12531625": {
				"blk": 6,
				"name": "Isaedum Onyx",
				"tur": 11,
				"type": "R"
			},
			"12531626": {
				"blk": 1,
				"mvp": 1,
				"name": "Souqur The Inquisitor",
				"rus": 3,
				"spp": 5,
				"tur": 3,
				"type": "R"
			},
			"12531627": {
				"blk": 4,
				"name": "Kiodhur Bloodworth",
				"tur": 16,
				"type": "R"
			},
			"12531628": {
				"blk": 5,
				"cas": 1,
				"cps": 1,
				"name": "Kexius Mortice",
				"rus": 2,
				"spp": 3,
				"tur": 16,
				"type": "R"
			},
			"12531629": {
				"blk": 2,
				"name": "Vrexor Rane",
				"tur": 16,
				"type": "R"
			},
			"12531630": {
				"blk": 1,
				"name": "Kradhur The Darkmaster",
				"tur": 8,
				"type": "R"
			},
			"12531631": {
				"blk": 1,
				"name": "Strebrum Crow",
				"tur": 10,
				"type": "R"
			},
			"12531634": {
				"blk": 1,
				"name": "Emaselm The Plaguemaster",
				"tur": 16,
				"type": "R"
			},
			"923590S1": {
				"blk": 5,
				"name": "Hack Enslash",
				"tur": 7,
				"type": "S"
			}
		}
	},
	"replayId": "1131312",
	"team_performance": {
		"919573": {
			"cas": 1,
			"casdiff": -2,
			"name": "Ragtag Animal Training Sartors",
			"rsym": "W",
			"score": 3,
			"scorediff": 3,
			"tds": 3,
			"tdsdiff": 3
		},
		"923590": {
			"cas": 3,
			"casdiff": 2,
			"name": "Temple Of Sorrow Tombstones",
			"rsym": "L",
			"score": 0,
			"scorediff": -3,
			"tds": 0,
			"tdsdiff": -3
		}
	}
}