{
	"!excluded": "no",
	"matchId": "4079713",
	"player": {
		"854678": {
			"11439624": {
				"blocks": 3,
				"dead": [
					2,
					6,
					"blocked",
					"12122276"
				],
				"name": "Grisnik the Blacktail",
				"prespp": 25,
				"turns": 13,
				"type": "R"
			},
			"11439628": {
				"blocks": 10,
				"cas": 1,
				"name": "Sneekis the Dragon",
				"prespp": 78,
				"spp": 2,
				"turns": 13,
				"type": "R"
			},
			"11482377": {
				"blocks": 2,
				"name": "Grisnagar the Brave",
				"prespp": 31,
				"turns": 15,
				"type": "R"
			},
			"11696956": {
				"blocks": 2,
				"name": "Nightmaster Skirshakk",
				"prespp": 157,
				"rush": 12,
				"spp": 3,
				"td": 1,
				"turns": 9,
				"type": "R"
			},
			"11850585": {
				"name": "Nightlord Azhiskikk",
				"prespp": 52,
				"type": "R"
			},
			"11934134": {
				"name": "Nightmaster Vasquee",
				"prespp": 62,
				"turns": 1,
				"type": "R"
			},
			"11951210": {
				"comp": 1,
				"name": "Nightlord Nurgrin",
				"pass": 2,
				"prespp": 85,
				"rush": 4,
				"spp": 1,
				"turns": 6,
				"type": "R"
			},
			"12217971": {
				"blocks": 1,
				"name": "Nightmaster Crittskik",
				"prespp": 56,
				"rush": 6,
				"turns": 3,
				"type": "R"
			},
			"12246149": {
				"name": "Raslik the Yellow",
				"prespp": 10,
				"turns": 7,
				"type": "R"
			},
			"12345916": {
				"fouls": 1,
				"mvp": 1,
				"name": "Vazhakk the Skywatcher",
				"prespp": 24,
				"spp": 5,
				"turns": 3,
				"type": "R"
			},
			"12528392": {
				"name": "Nightmaster Skre",
				"prespp": 27,
				"type": "R"
			},
			"12528405": {
				"name": "Khrat the Nightfury",
				"turns": 15,
				"type": "R"
			},
			"12540527": {
				"blocks": 1,
				"name": "Skik the Weaver",
				"prespp": 7,
				"turns": 4,
				"type": "R"
			},
			"12616877": {
				"name": "Thueet the Crow",
				"turns": 8,
				"type": "R"
			},
			"12616878": {
				"name": "Crilk the Eager",
				"turns": 16,
				"type": "R"
			},
			"12706917": {
				"name": "Chuzhak the Rough",
				"turns": 3,
				"type": "R"
			}
		},
		"897376": {
			"12122272": {
				"blocks": 9,
				"cas": 2,
				"name": "Dark Shade",
				"prespp": 60,
				"rush": 1,
				"spp": 4,
				"turns": 16,
				"type": "R"
			},
			"12122273": {
				"blocks": 12,
				"name": "Deep Root",
				"prespp": 38,
				"turns": 16,
				"type": "R"
			},
			"12122274": {
				"blocks": 6,
				"name": "Long Branch",
				"prespp": 35,
				"turns": 9,
				"type": "R"
			},
			"12122276": {
				"blocks": 2,
				"cas": 1,
				"name": "White Leaf",
				"prespp": 40,
				"rush": 21,
				"spp": 5,
				"td": 1,
				"turns": 16,
				"type": "R"
			},
			"12122280": {
				"blocks": 1,
				"fouls": 4,
				"name": "Lichen",
				"prespp": 16,
				"turns": 16,
				"type": "R"
			},
			"12168335": {
				"blocks": 6,
				"mvp": 1,
				"name": "Gray Timber",
				"prespp": 42,
				"rush": 11,
				"spp": 8,
				"td": 1,
				"turns": 16,
				"type": "R"
			},
			"12171988": {
				"name": "Nut",
				"prespp": 21,
				"turns": 3,
				"type": "R"
			},
			"12497695": {
				"blocks": 4,
				"name": "Ivy",
				"prespp": 15,
				"turns": 16,
				"type": "R"
			},
			"12501405": {
				"blocks": 7,
				"name": "Fruit",
				"prespp": 7,
				"turns": 16,
				"type": "R"
			},
			"12515971": {
				"blocks": 1,
				"cas": 1,
				"name": "Vine",
				"prespp": 3,
				"spp": 2,
				"turns": 1,
				"type": "R"
			},
			"12529934": {
				"name": "Fungus",
				"type": "R"
			},
			"12529938": {
				"blocks": 7,
				"name": "Slip Stream",
				"prespp": 6,
				"turns": 16,
				"type": "R"
			},
			"12559341": {
				"blocks": 2,
				"name": "Hollow",
				"prespp": 12,
				"turns": 12,
				"type": "R"
			},
			"12580870": {
				"name": "Shoot",
				"type": "R"
			},
			"12710019": {
				"name": "Crooked Creek",
				"type": "R"
			}
		}
	},
	"replayId": "1172869",
	"team": {
		"854678": {
			"blocks": 19,
			"cas": 1,
			"casdiff": -5,
			"comp": 1,
			"fouls": 1,
			"int": 0,
			"mvp": 1,
			"name": "Lords of the Silent Death",
			"pass": 2,
			"prespp": 614,
			"prestige": 0,
			"pts": 0,
			"r": "L",
			"rush": 22,
			"score": 1,
			"scorediff": -1,
			"td": 1,
			"tddiff": -1,
			"turns": 116
		},
		"897376": {
			"blocks": 57,
			"cas": 6,
			"casdiff": 5,
			"comp": 0,
			"fouls": 4,
			"int": 0,
			"mvp": 1,
			"name": "Darkenwood Sentinels",
			"pass": 0,
			"prespp": 295,
			"prestige": 30,
			"pts": 3,
			"r": "W",
			"rush": 33,
			"score": 2,
			"scorediff": 1,
			"td": 2,
			"tddiff": 1,
			"turns": 153
		}
	}
}