{
	"!excluded": "no",
	"matchId": "4113482",
	"player": {
		"874317": {
			"11754410": {
				"blocks": 9,
				"cas": 1,
				"name": "Odracon The Procreator",
				"prespp": 102,
				"spp": 2,
				"turns": 16,
				"type": "R"
			},
			"11754414": {
				"blocks": 1,
				"fouls": 2,
				"name": "Lug",
				"prespp": 7,
				"turns": 8,
				"type": "R"
			},
			"11754417": {
				"name": "Cethlenn",
				"prespp": 14,
				"turns": 3,
				"type": "R"
			},
			"11754418": {
				"blocks": 5,
				"name": "Tethra",
				"prespp": 32,
				"turns": 8,
				"type": "R"
			},
			"11904321": {
				"blocks": 1,
				"name": "Dilek",
				"prespp": 83,
				"rush": 7,
				"turns": 14,
				"type": "R"
			},
			"12047952": {
				"blocks": 12,
				"cas": 2,
				"name": "Slough Feg",
				"prespp": 81,
				"spp": 4,
				"turns": 16,
				"type": "R"
			},
			"12126092": {
				"blocks": 1,
				"name": "Hadiz",
				"prespp": 77,
				"rush": 13,
				"spp": 3,
				"td": 1,
				"turns": 9,
				"type": "R"
			},
			"12239695": {
				"blocks": 11,
				"name": "Moloch the 3rd",
				"prespp": 64,
				"turns": 16,
				"type": "R"
			},
			"12340697": {
				"name": "Foulloch",
				"turns": 3,
				"type": "R"
			},
			"12537776": {
				"blocks": 4,
				"name": "Cromcraug",
				"prespp": 15,
				"turns": 16,
				"type": "R"
			},
			"12537777": {
				"name": "Kakt",
				"prespp": 16,
				"turns": 16,
				"type": "R"
			},
			"12618155": {
				"blocks": 2,
				"name": "Finn Fimm",
				"prespp": 20,
				"turns": 16,
				"type": "R"
			},
			"12624220": {
				"blocks": 6,
				"name": "Medb",
				"prespp": 9,
				"turns": 16,
				"type": "R"
			},
			"12721386": {
				"blocks": 1,
				"mvp": 1,
				"name": "Rolab Everlast",
				"prespp": 15,
				"spp": 5,
				"turns": 5,
				"type": "R"
			}
		},
		"879131": {
			"11828950": {
				"blocks": 13,
				"cas": 1,
				"name": "Calico Jack",
				"prespp": 153,
				"rush": 7,
				"spp": 2,
				"turns": 16,
				"type": "R"
			},
			"11828951": {
				"blocks": 5,
				"name": "Morag",
				"prespp": 58,
				"turns": 16,
				"type": "B"
			},
			"11828952": {
				"blocks": 4,
				"name": "Greta",
				"prespp": 50,
				"turns": 13,
				"type": "B"
			},
			"11828954": {
				"blocks": 1,
				"name": "Ibhib Nightbreaker",
				"pass": -1,
				"prespp": 163,
				"rush": 17,
				"spp": 3,
				"td": 1,
				"turns": 14,
				"type": "R"
			},
			"11828955": {
				"blocks": 10,
				"cas": 1,
				"name": "Dog Rough Drimond",
				"prespp": 77,
				"spp": 2,
				"turns": 15,
				"type": "R"
			},
			"11828956": {
				"blocks": 7,
				"name": "Grog Swiller Finn",
				"prespp": 84,
				"turns": 16,
				"type": "R"
			},
			"12426661": {
				"name": "Mutiny Bryce",
				"prespp": 13,
				"turns": 1,
				"type": "R"
			},
			"12493747": {
				"blocks": 1,
				"name": "Chains Mullaney",
				"prespp": 2,
				"turns": 4,
				"type": "R"
			},
			"12517082": {
				"blocks": 1,
				"comp": 1,
				"name": "Dounnoth Stormarrow",
				"pass": 2,
				"prespp": 54,
				"rush": -1,
				"spp": 1,
				"turns": 14,
				"type": "R"
			},
			"12582863": {
				"blocks": 2,
				"name": "Bluntfist Crockett",
				"prespp": 6,
				"turns": 16,
				"type": "R"
			},
			"12610891": {
				"name": "Cabin Boy Sullivan",
				"type": "R"
			},
			"12670925": {
				"name": "Frankie Drake",
				"turns": 4,
				"type": "R"
			},
			"12884766": {
				"mvp": 1,
				"name": "Gibbet O'Sullivan",
				"prespp": 2,
				"spp": 5,
				"type": "R"
			},
			"12892634": {
				"name": "Tank Murdock",
				"retired": true,
				"turns": 5,
				"type": "R"
			},
			"12938231": {
				"blocks": 1,
				"name": "Eddie \"The Eagle\" Teach",
				"turns": 12,
				"type": "R"
			},
			"STAR-Boomer Eziasson": {
				"name": "Boomer Eziasson",
				"turns": 8,
				"type": "S"
			}
		}
	},
	"replayId": "1211357",
	"team": {
		"874317": {
			"blocks": 53,
			"cas": 3,
			"casdiff": 1,
			"comp": 0,
			"fouls": 2,
			"int": 0,
			"mvp": 1,
			"name": "Misty Isle Gators",
			"pass": 0,
			"prespp": 535,
			"prestige": 10,
			"pts": 1,
			"r": "D",
			"rush": 20,
			"score": 1,
			"scorediff": 0,
			"td": 1,
			"tddiff": 0,
			"turns": 162
		},
		"879131": {
			"blocks": 45,
			"cas": 2,
			"casdiff": -1,
			"comp": 1,
			"fouls": 0,
			"int": 0,
			"mvp": 1,
			"name": "Sartosa Black Flags",
			"pass": 1,
			"prespp": 662,
			"prestige": 10,
			"pts": 1,
			"r": "D",
			"rush": 23,
			"score": 1,
			"scorediff": 0,
			"td": 1,
			"tddiff": 0,
			"turns": 154
		}
	}
}