{
	"!excluded": "no",
	"!locked": "yes",
	"matchId": "3890546",
	"player_performance": {
		"854502": {
			"11436807": {
				"blk": 1,
				"name": "Oblomov IV",
				"prespp": 14,
				"tur": 3,
				"type": "R"
			},
			"11436813": {
				"name": "Lev Nikolájevitj Mýsjkin",
				"prespp": 5,
				"retired": true,
				"tur": 5,
				"type": "R"
			},
			"11436823": {
				"blk": 4,
				"name": "Antíp Lev Burdóvskij",
				"prespp": 10,
				"tur": 14,
				"type": "R"
			},
			"11436825": {
				"blk": 2,
				"name": "Ardalión Iván Aleksándrovitj",
				"prespp": 6,
				"tur": 8,
				"type": "R"
			},
			"11436826": {
				"blk": 3,
				"name": "Gavríla Gánja Ardaliónovitj",
				"prespp": 13,
				"rus": 6,
				"tur": 14,
				"type": "R"
			},
			"11436827": {
				"blk": 8,
				"name": "Iván Fjódorovitj Jepantjín",
				"prespp": 10,
				"tur": 16,
				"type": "R"
			},
			"11436828": {
				"blk": 2,
				"dead": [
					1,
					3,
					"blocked",
					"11580218"
				],
				"name": "Lukján Timoféjevitj Lébedjev",
				"prespp": 31,
				"tur": 2,
				"type": "R"
			},
			"11436832": {
				"blk": 2,
				"cas": 1,
				"cps": 1,
				"mvp": 1,
				"name": "Nikoláj Andréj Pavlísjtjev",
				"pas": 1,
				"prespp": 10,
				"rus": 17,
				"spp": 8,
				"tur": 17,
				"type": "R"
			},
			"11436836": {
				"name": "Parfjón Semjónovitj Rogózjin",
				"prespp": 9,
				"tur": 1,
				"type": "R"
			},
			"11493956": {
				"blk": 3,
				"name": "Grigor",
				"prespp": 6,
				"tur": 9,
				"type": "R"
			},
			"11592707": {
				"blk": 2,
				"fou": 1,
				"name": "Ilja Petrovitj",
				"prespp": 2,
				"tur": 10,
				"type": "R"
			},
			"11708599": {
				"blk": 4,
				"name": "Górstkin Ljagávyj",
				"tur": 14,
				"type": "R"
			},
			"11708604": {
				"blk": 3,
				"name": "Ippolít Kiríllovitj",
				"prespp": 2,
				"tur": 10,
				"type": "R"
			}
		},
		"859122": {
			"11512890": {
				"blk": 14,
				"mvp": 1,
				"name": "Logan Willow",
				"prespp": 17,
				"spp": 5,
				"tur": 18,
				"type": "R"
			},
			"11512891": {
				"blk": 8,
				"name": "Archer Maddison",
				"prespp": 7,
				"retired": true,
				"tur": 18,
				"type": "R"
			},
			"11512892": {
				"blk": 3,
				"cas": 1,
				"name": "Jackson Violet",
				"prespp": 7,
				"rus": 6,
				"spp": 2,
				"tur": 10,
				"type": "R"
			},
			"11512894": {
				"blk": 1,
				"name": "Alexander Tyler",
				"prespp": 9,
				"rus": 24,
				"spp": 3,
				"tds": 1,
				"tur": 16,
				"type": "R"
			},
			"11512896": {
				"blk": 4,
				"name": "Hugo Hunter",
				"prespp": 10,
				"rus": 4,
				"spp": 3,
				"tds": 1,
				"tur": 18,
				"type": "R"
			},
			"11512898": {
				"blk": 3,
				"fou": 1,
				"name": "Oscar Jayden",
				"prespp": 2,
				"tur": 10,
				"type": "R"
			},
			"11512907": {
				"blk": 1,
				"fou": 1,
				"name": "Alan Berkley",
				"prespp": 4,
				"tur": 6,
				"type": "R"
			},
			"11512909": {
				"fou": 2,
				"name": "Michael Summer",
				"prespp": 22,
				"tur": 9,
				"type": "R"
			},
			"11512911": {
				"blk": 2,
				"cas": 1,
				"name": "Ellie Mackenzie",
				"prespp": 10,
				"spp": 2,
				"tur": 10,
				"type": "R"
			},
			"11512914": {
				"blk": 10,
				"name": "Jaxon Piper",
				"prespp": 19,
				"tur": 18,
				"type": "R"
			},
			"11580218": {
				"blk": 1,
				"cas": 1,
				"fou": 1,
				"name": "Edward Riley",
				"prespp": 2,
				"spp": 2,
				"tur": 3,
				"type": "R"
			},
			"11598373": {
				"blk": 3,
				"name": "Flynn Nate",
				"prespp": 3,
				"tur": 18,
				"type": "R"
			},
			"11693778": {
				"blk": 1,
				"name": "Fiergusson Downy",
				"tur": 10,
				"type": "R"
			},
			"11693781": {
				"name": "Joey Downy",
				"prespp": 5,
				"tur": 10,
				"type": "R"
			},
			"11708446": {
				"name": "Leonard Downy",
				"type": "R"
			}
		}
	},
	"replayId": "954200",
	"team_performance": {
		"854502": {
			"cas": 1,
			"casdiff": -3,
			"name": "Spartak Bolgasgrad",
			"rsym": "L",
			"score": 0,
			"scorediff": -2,
			"tds": 0,
			"tdsdiff": -2
		},
		"859122": {
			"cas": 4,
			"casdiff": 3,
			"name": "Flying Drop Bears",
			"rsym": "W",
			"score": 2,
			"scorediff": 2,
			"tds": 2,
			"tdsdiff": 2
		}
	}
}